kess/__init__.py
kess/actor.py
kess/app.py
kess/asyncio.py
kess/env.py
kess/exceptions.py
kess/function.py
kess/imports.py
kess/invocation.py
kess-0.14.0.dist-info/WHEEL
kess-0.14.0.dist-info/METADATA
kess-0.14.0.dist-info/RECORD
