Metadata-Version: 2.1
Name: kess
Version: 0.14.0
Summary: 
Author: majik
Author-email: me@yamajik.com
Requires-Python: >=3.8,<4.0
Classifier: Programming Language :: Python :: 3
Classifier: Programming Language :: Python :: 3.8
Classifier: Programming Language :: Python :: 3.9
Requires-Dist: dapr (>=1.0.0,<2.0.0)
Requires-Dist: dapr-ext-fastapi (>=1.0.0,<2.0.0)
Requires-Dist: fastapi (>=0.63.0,<0.64.0)
